senziio/__init__.py
senziio/exceptions.py
senziio/senziio.py
senziio-0.0.1.dist-info/LICENSE
senziio-0.0.1.dist-info/METADATA
senziio-0.0.1.dist-info/WHEEL
senziio-0.0.1.dist-info/top_level.txt
senziio-0.0.1.dist-info/RECORD
