Metadata-Version: 2.1
Name: senziio
Version: 0.0.1
Summary: Support libraries for the Senziio Theia device integration with Home Assistant.
Author-email: Federico Zuccolo <federico.zuccolo@gmail.com>
License: Apache License
Project-URL: Homepage, https://github.com/senziio-admin/python-senziio-ha
Project-URL: Issues, https://github.com/senziio-admin/python-senziio-ha/issues
Classifier: Programming Language :: Python :: 3.10
Classifier: Programming Language :: Python :: 3.11
Classifier: Programming Language :: Python :: 3.12
Classifier: License :: OSI Approved :: Apache Software License
Classifier: Operating System :: OS Independent
Requires-Python: >=3.10
License-File: LICENSE
Provides-Extra: dev
Requires-Dist: pytest ; extra == 'dev'
Requires-Dist: pytest-cov ; extra == 'dev'
Requires-Dist: flake8 ; extra == 'dev'
